<?xml version="1.0" encoding="UTF-8" standalone="yes"?>
<servico xmlns="http://servicos.gov.br/v3/schema" xmlns:xsi="http://www.w3.org/2001/XMLSchema-instance" xsi:schemaLocation="http://servicos.gov.br/v3/schema.../servico.xsd">
    <id>atividades-culturais-e-pedagogicas-no-campo-das-relacoes-internacionais</id>
    <dbId>895</dbId>
    <nome>inscrever-se-em-atividades-do-programa-anual-de-trabalho-da-funag</nome>
    <sigla/>
    <nomes-populares>
        <item id="698">Seminários</item>
        <item id="699">Palestras</item>
        <item id="700">Debates</item>
        <item id="701">Conferência</item>
        <item id="702">Mesa-redonda</item>
        <item id="703">Relações Internacionais</item>
        <item id="704">Relações exteriores</item>
        <item id="705">Diplomacia</item>
    </nomes-populares>
    <descricao>São disponibilizadas informações e inscrições sobre as atividades que integram o Programa de Trabalho Anual da FUNAG (palestras, debates, seminários, conferências e outros sobre o tema das relações internacionais, política externa e história diplomática brasileira..</descricao>
    <contato>* Fundação Alexandre de Gusmão
* Endereço: Esplanada dos Ministérios, Bloco "H" - Anexo II, Térreo
* CEP: 70170-900       CNPJ: 00662197/0001-24
* Telefones: (61)2030-6033/6034/6820/6847  /  Fax: (61)2030-9125
* E-mail: funag@funag.gov.br  /  funag@itamaraty.gov.br
* Horário de funcionamento: Seg a Sex das 8h às 18h</contato>
    <gratuito>true</gratuito>
    <porcentagem-digital>0</porcentagem-digital>
    <solicitantes>
        <solicitante id="922">
            <tipo>Qualquer cidadão interessado em participar atividade cultural no campo das relações internacionais</tipo>
            <requisitos/>
        </solicitante>
    </solicitantes>
    <tempo-total-estimado>
        <atendimento-imediato/>
        <descricao/>
    </tempo-total-estimado>
    <validade-documento>
        <tipo>Sem validade</tipo>
        <quantidade>0</quantidade>
        <unidade/>
        <descricao/>
    </validade-documento>
    <etapas>
        <etapa id="2325">
            <titulo>Inscrever-se na atividade/evento</titulo>
            <descricao>* Acessar a [página de inscrições para atividades/eventos](http://www.funag.gov.br/sisev)
* Caso possua cadastro no sistema, entrar com usuário (e-mail) e senha
* Caso não possua cadastro, clicar no ícone "cadastre-se aqui" e preencher o formulário de cadastro
*  Ao acessar o sistema com o usuário e senha, clicar em "eventos abertos" e inscrever-se na atividade que tenha interesse
*  Comparecer ao local, na data e hora especificada e participar da atividade</descricao>
            <documentos>
                <default>
                    <item id="2547">CPF</item>
                    <item id="2548">RG</item>
                    <item id="2549">Endereço de Residência</item>
                </default>
            </documentos>
            <custos>
                <default/>
            </custos>
            <canais-de-prestacao>
                <default>
                    <canal-de-prestacao id="2964" tipo="web">
                        <descricao>http://funag.gov.br/sisev/</descricao>
                    </canal-de-prestacao>
                </default>
            </canais-de-prestacao>
        </etapa>
    </etapas>
    <orgao id="299"/>
    <segmentos-da-sociedade>
        <item idSegmento="1" idServicoSegmento="2636">Cidadãos</item>
        <item idSegmento="3" idServicoSegmento="2637">Empresas</item>
        <item idSegmento="2" idServicoSegmento="2638">Órgãos e entidades públicas</item>
        <item idSegmento="4" idServicoSegmento="2639">Demais segmentos (ONGs, organizações sociais, etc)</item>
    </segmentos-da-sociedade>
    <areas-de-interesse>
        <item>Comercio externo</item>
        <item>Difusão Cultural</item>
        <item>Educação</item>
        <item>Educação profissionalizante</item>
        <item>Pesquisa e Desenvolvimento</item>
        <item>Relações Diplomáticas</item>
        <item>Clima</item>
        <item>Comércio e Serviços</item>
        <item>Cultura</item>
        <item>Defesa Nacional</item>
        <item>Economia e Finanças</item>
        <item>Educação básica</item>
        <item>Educação superior</item>
        <item>Energia</item>
        <item>Fomento ao Trabalho</item>
        <item>Meio ambiente</item>
        <item>Relações Internacionais</item>
    </areas-de-interesse>
    <palavras-chave>
        <item id="2216">relações internacionais</item>
        <item id="2217">relações exteriores</item>
        <item id="2218">diplomacia</item>
        <item id="2219">eventos</item>
        <item id="2220">palestras</item>
        <item id="2221">debates</item>
        <item id="2222">seminários</item>
        <item id="2223">mesa-redonda</item>
        <item id="2224">conferências</item>
    </palavras-chave>
    <legislacoes>
        <item id="741">http://funag.gov.br/index.php/pt-br/legislacao</item>
    </legislacoes>
</servico>
