<?xml version="1.0" encoding="UTF-8" standalone="yes"?>
<servico xsi:schemaLocation="http://servicos.gov.br/v3/schema.../servico.xsd" xmlns="http://servicos.gov.br/v3/schema" xmlns:xsi="http://www.w3.org/2001/XMLSchema-instance">
    <id>centro-lucio-costa</id>
    <dbId>856</dbId>
    <nome>Centro Lucio Costa</nome>
    <sigla>CLC</sigla>
    <descricao>O Centro Lucio Costa – CLC é um Centro Regional de Treinamento e Gestão – Categoria 2, criado
a partir do acordo firmado entre o Governo do Brasil e a Organização das Nações Unidas para a
Educação, Ciência e Cultura – UNESCO.</descricao>
    <contato>Presencial: Palácio Gustavo Capanema - Rua da Imprensa, nº 16, 9º andar, Centro, Rio de Janeiro-RJ, CEP:20.030-120.
Telefones: (21) 2215-3805/3578.
Virtual: http://portal.iphan.gov.br, ou Por e-mail: centro.luciocosta@iphan.gov.br</contato>
    <gratuito>true</gratuito>
    <porcentagem-digital>0</porcentagem-digital>
    <solicitantes>
        <solicitante id="883">
            <tipo>Cidadão</tipo>
            <requisitos></requisitos>
        </solicitante>
    </solicitantes>
    <tempo-total-estimado>
        <atendimento-imediato/>
        <descricao></descricao>
    </tempo-total-estimado>
    <validade-documento/>
    <etapas>
        <etapa id="2295">
            <titulo>Treinamento e Gestão</titulo>
            <descricao></descricao>
            <documentos>
                <default/>
            </documentos>
            <custos>
                <default/>
            </custos>
            <canais-de-prestacao>
                <default>
                    <canal-de-prestacao id="2905" tipo="e-mail">
                        <descricao>centro.luciocosta@iphan.gov.br</descricao>
                    </canal-de-prestacao>
                    <canal-de-prestacao id="2904" tipo="web">
                        <descricao>http://portal.iphan.gov.br,</descricao>
                    </canal-de-prestacao>
                    <canal-de-prestacao id="2903" tipo="telefone">
                        <descricao>(21) 2215-3805/3578.</descricao>
                    </canal-de-prestacao>
                    <canal-de-prestacao id="2902" tipo="presencial">
                        <descricao>Palácio Gustavo Capanema - Rua da Imprensa, nº 16, 9º andar, Centro, Rio de Janeiro-RJ, CEP: 20.030-120.</descricao>
                    </canal-de-prestacao>
                </default>
            </canais-de-prestacao>
        </etapa>
    </etapas>
    <orgao id="2045"/>
    <segmentos-da-sociedade>
        <item idSegmento="1" idServicoSegmento="2498">Cidadãos</item>
        <item idSegmento="3" idServicoSegmento="2499">Empresas</item>
        <item idSegmento="2" idServicoSegmento="2500">Órgãos e entidades públicas</item>
        <item idSegmento="4" idServicoSegmento="2501">Demais segmentos (ONGs, organizações sociais, etc)</item>
    </segmentos-da-sociedade>
    <areas-de-interesse>
        <item>Cultura</item>
        <item>Difusão Cultural</item>
        <item>Patrimônio Cultural</item>
    </areas-de-interesse>
    <palavras-chave>
        <item id="2061">Centro Lucio Costa</item>
        <item id="2062">CLC</item>
        <item id="2063">IPHAN</item>
    </palavras-chave>
    <legislacoes>
        <item id="714">Não se aplica.</item>
    </legislacoes>
</servico>
