<?xml version="1.0" encoding="UTF-8" standalone="no"?>
<servico xmlns="http://servicos.gov.br/v3/schema" xmlns:xsi="http://www.w3.org/2001/XMLSchema-instance" xsi:schemaLocation="http://servicos.gov.br/v3/schema ../servico.xsd">
    <nome>fabricio teste</nome>
    <sigla>ft</sigla>
    <nomes-populares/>
    <descricao>asdfasdfa</descricao>
    <gratuito>false</gratuito>
    <solicitantes>
        <solicitante>
            <tipo>asafsdf</tipo>
            <requisitos/>
        </solicitante>
    </solicitantes>
    <tempo-total-estimado>
        <ate max="4" unidade="horas"/>
        <descricao/>
    </tempo-total-estimado>
    <etapas>
        <etapa>
            <titulo>fghfgh</titulo>
            <descricao/>
            <documentos>
                <default/>
            </documentos>
            <custos>
                <default>
                    <custo>
                        <descricao>vbmvbnm</descricao>
                        <moeda/>
                        <valor>10,00</valor>
                    </custo>
                </default>
            </custos>
            <canais-de-prestacao>
                <default>
                    <canal-de-prestacao tipo="e-mail">
                        <descricao>mvbm@gsfg</descricao>
                    </canal-de-prestacao>
                </default>
            </canais-de-prestacao>
        </etapa>
    </etapas>
    <orgao id="http://estruturaorganizacional.dados.gov.br/id/unidade-organizacional/63249">
        <contato/>
    </orgao>
    <segmentos-da-sociedade>
        <item>Cidadãos</item>
    </segmentos-da-sociedade>
    <areas-de-interesse>
        <item>Abastecimento</item>
    </areas-de-interesse>
    <palavras-chave>
        <item>adfasdf</item>
        <item>xcbvxc</item>
        <item>bxvcb</item>
    </palavras-chave>
    <legislacoes>
        <item>ghkghk</item>
    </legislacoes>
</servico>