<?xml version="1.0" encoding="UTF-8" standalone="yes"?>
<servico xsi:schemaLocation="http://servicos.gov.br/v3/schema.../servico.xsd" xmlns="http://servicos.gov.br/v3/schema" xmlns:xsi="http://www.w3.org/2001/XMLSchema-instance">
    <id>obter-desoneracao-tributaria-para-mercadorias-destinadas-a-industrializacao-de-produto-a-ser-exportado</id>
    <dbId>1018</dbId>
    <nome>Obter desoneração tributária para mercadorias destinadas à industrialização de produto a ser exportado.</nome>
    <sigla></sigla>
    <nomes-populares>
        <item id="1363">Drawback suspensão</item>
    </nomes-populares>
    <descricao>Regime Aduaneiro Especial que permite a suspensão na aquisição no mercado interno ou na importação, de forma combinada ou não, de mercadoria para emprego ou consumo na industrialização de produto a ser exportado, com suspensão dos tributos exigíveis na importação e na aquisição no mercado interno.</descricao>
    <contato></contato>
    <gratuito>true</gratuito>
    <porcentagem-manual>false</porcentagem-manual>
    <servico-digital>false</servico-digital>
    <link-servico-digital></link-servico-digital>
    <tempo-total-estimado>
        <entre min="16" max="30" unidade="dias-corridos"/>
        <descricao></descricao>
    </tempo-total-estimado>
    <validade-documento>
        <descricao></descricao>
    </validade-documento>
    <etapas/>
    <orgao id="http://estruturaorganizacional.dados.gov.br/id/unidade-organizacional/3162" dbId="37530">
        <nomeOrgao>Ministério da Indústria, Comércio Exterior e Serviços (MDIC)</nomeOrgao>
    </orgao>
    <areas-de-interesse>
        <item>Comércio e Serviços</item>
        <item>Comercio externo</item>
        <item>Fiscalização do Estado</item>
        <item>Produção Industrial</item>
    </areas-de-interesse>
</servico>
