<?xml version="1.0" encoding="UTF-8" standalone="yes"?>
<servico xsi:schemaLocation="http://servicos.gov.br/v3/schema.../servico.xsd" xmlns="http://servicos.gov.br/v3/schema" xmlns:xsi="http://www.w3.org/2001/XMLSchema-instance">
    <id>obter-aprovacao-de-grande-modificacao-desenvolvida-pelo-detentor-do-certificado-de-tipo</id>
    <dbId>3137</dbId>
    <nome>Obter Aprovação de Grande Modificação desenvolvida pelo detentor do Certificado de Tipo</nome>
    <sigla></sigla>
    <descricao>Aprovar Grande Modificação desenvolvida pelo detentor do Certificado de Tipo significa que o projeto de tipo modificado tem nível de segurança aceitável</descricao>
    <contato></contato>
    <gratuito>true</gratuito>
    <porcentagem-manual>false</porcentagem-manual>
    <servico-digital>false</servico-digital>
    <link-servico-digital></link-servico-digital>
    <solicitantes>
        <solicitante id="3723">
            <tipo>Detentor do Certificado de Tipo</tipo>
            <requisitos></requisitos>
        </solicitante>
    </solicitantes>
    <tempo-total-estimado>
        <entre min="16" max="30" unidade="dias-corridos"/>
        <descricao></descricao>
    </tempo-total-estimado>
    <validade-documento>
        <descricao></descricao>
    </validade-documento>
    <etapas>
        <etapa id="7133">
            <titulo>Solicitar aprovação</titulo>
            <descricao>Enviar a solicitação de aprovação e submeter dados técnicos</descricao>
            <documentos>
                <default>
                    <item id="9960">Solicitação de Aprovação</item>
                    <item id="9961">Documentação Técnica</item>
                    <item id="9962">Certificado de Tipo</item>
                </default>
            </documentos>
            <custos>
                <default/>
            </custos>
            <canais-de-prestacao>
                <default>
                    <canal-de-prestacao id="7494" tipo="postal">
                        <descricao>**Agência Nacional de Aviação Civil - Superintendência de Aeronavegabilidade - Gerência Geral de Certificação de Produtos Aeronáuticos** - Rua Laurent Martins, 209 - Jardim Esplanada - CEP: 12242-431 - São José dos Campos - SP</descricao>
                    </canal-de-prestacao>
                </default>
            </canais-de-prestacao>
        </etapa>
    </etapas>
    <orgao id="http://estruturaorganizacional.dados.gov.br/id/unidade-organizacional/86144" dbId="908">
        <nomeOrgao>Agência Nacional de Aviação Civil (ANAC)</nomeOrgao>
    </orgao>
    <segmentos-da-sociedade>
        <item idSegmento="1" idServicoSegmento="7050">Cidadãos</item>
        <item idSegmento="3" idServicoSegmento="7051">Empresas</item>
    </segmentos-da-sociedade>
    <areas-de-interesse>
        <item>Pesquisa e Desenvolvimento</item>
        <item>Relações Internacionais</item>
        <item>Transportes</item>
        <item>Indústria</item>
        <item>Transporte Aéreo</item>
    </areas-de-interesse>
    <palavras-chave>
        <item id="13114">mudança de projeto</item>
        <item id="13115">aviação</item>
        <item id="13116">anac</item>
    </palavras-chave>
</servico>
