<?xml version="1.0" encoding="UTF-8" standalone="yes"?>
<servico xsi:schemaLocation="http://servicos.gov.br/v3/schema.../servico.xsd" xmlns="http://servicos.gov.br/v3/schema" xmlns:xsi="http://www.w3.org/2001/XMLSchema-instance">
    <id>obter-direito-real-de-uso-para-populacoes-tradicionais</id>
    <dbId>2985</dbId>
    <nome>Obter Direito Real de Uso para populações tradicionais</nome>
    <sigla></sigla>
    <descricao>A Concessão de Direito Real de Uso trata-se  de um contrato administrativo pelo qual o Poder Publico atribui um bem de seu domínio a particular, para que explore segundo a sua destinação específica. É um título de uso dos recursos naturais repassado pelo Governo,  no caso o Federal, para as organizações representativas e famílias de comunidades tradicionais residentes em uma Unidade de Conservação de uso sustentável-Reservas Extrativistas, Reservas de Desenvolvimento Sustentável e Florestas Nacionais.</descricao>
    <contato></contato>
    <gratuito>true</gratuito>
    <porcentagem-manual>false</porcentagem-manual>
    <servico-digital>false</servico-digital>
    <link-servico-digital></link-servico-digital>
    <solicitantes>
        <solicitante id="3570">
            <tipo>Famílias de comunidades tradicionais residentes em uma Unidade de Conservação de uso sustentável ou suas organizações representativas.</tipo>
            <requisitos></requisitos>
        </solicitante>
    </solicitantes>
    <tempo-total-estimado>
        <entre min="60" max="90" unidade="dias-corridos"/>
        <descricao></descricao>
    </tempo-total-estimado>
    <validade-documento>
        <descricao></descricao>
    </validade-documento>
    <etapas>
        <etapa id="6870">
            <titulo>Requerer Direito Real de Uso</titulo>
            <descricao>Participação da Associação Concessionária, representada pelo seu presidente, em  reunião do Conselho da Unidade de Conservação</descricao>
            <documentos>
                <default>
                    <item id="9302">Ata de fundação</item>
                    <item id="9303">Carteira de identidade</item>
                    <item id="9304">Carteira de trabalho</item>
                    <item id="9305">CNPJ</item>
                    <item id="9306">CPF</item>
                    <item id="9307">Estatuto da Associação Concessionária</item>
                </default>
            </documentos>
            <custos>
                <default/>
            </custos>
            <canais-de-prestacao>
                <default>
                    <canal-de-prestacao id="7133" tipo="telefone">
                        <descricao>(61) 2028-9330</descricao>
                    </canal-de-prestacao>
                </default>
            </canais-de-prestacao>
        </etapa>
    </etapas>
    <orgao id="http://estruturaorganizacional.dados.gov.br/id/unidade-organizacional/91842" dbId="36726">
        <nomeOrgao>Instituto Chico Mendes de Conservação da Biodiversidade (ICMBio)</nomeOrgao>
    </orgao>
    <segmentos-da-sociedade>
        <item idSegmento="1" idServicoSegmento="6781">Cidadãos</item>
    </segmentos-da-sociedade>
    <areas-de-interesse>
        <item>Proteção Social</item>
        <item>Habitação</item>
        <item>Meio ambiente</item>
        <item>Preservação e Conservação Ambiental</item>
        <item>Patrimônio da União</item>
    </areas-de-interesse>
    <palavras-chave>
        <item id="12723">indíos</item>
        <item id="12724">terra</item>
        <item id="12725">direito</item>
    </palavras-chave>
</servico>
