<?xml version="1.0" encoding="UTF-8" standalone="yes"?>
<servico xsi:schemaLocation="http://servicos.gov.br/v3/schema.../servico.xsd" xmlns="http://servicos.gov.br/v3/schema" xmlns:xsi="http://www.w3.org/2001/XMLSchema-instance">
    <id>obter-incentivos-fiscais-para-empresas-que-lidam-com-desenvolvimento-tecnologico-e-inovacao</id>
    <dbId>1442</dbId>
    <nome>Obter incentivos fiscais para empresas que lidam com desenvolvimento tecnológico e inovação</nome>
    <sigla></sigla>
    <descricao>Através deste serviço, a empresa que lida com desenvolvimento tecnológico e inovação pode pleitear incentivos fiscais.</descricao>
    <contato></contato>
    <gratuito>true</gratuito>
    <porcentagem-manual>false</porcentagem-manual>
    <servico-digital>false</servico-digital>
    <link-servico-digital></link-servico-digital>
    <solicitantes>
        <solicitante id="1797">
            <tipo>Empresas que operam no regime fiscal do Lucro Real</tipo>
            <requisitos></requisitos>
        </solicitante>
    </solicitantes>
    <tempo-total-estimado>
        <ate max="12" unidade="meses"/>
        <descricao></descricao>
    </tempo-total-estimado>
    <validade-documento>
        <descricao></descricao>
    </validade-documento>
    <etapas>
        <etapa id="3814">
            <titulo>Requisitar incentivo fiscal</titulo>
            <descricao>Apresentação do Relatório FORMP&amp;D devidamente preenchido.</descricao>
            <documentos>
                <default>
                    <item id="5625">Relatório FORMP&amp;D</item>
                </default>
            </documentos>
            <custos>
                <default/>
            </custos>
            <canais-de-prestacao>
                <default>
                    <canal-de-prestacao id="4803" tipo="e-mail">
                        <descricao>incentivos.fiscais@mctic.gov.br</descricao>
                    </canal-de-prestacao>
                    <canal-de-prestacao id="4804" tipo="postal">
                        <descricao>Secretaria de Desenvolvimento Tecnológico e Inovação – SETEC
Esplanada dos Mistérios, Bloco, sala 373
CEP - 70067-900</descricao>
                    </canal-de-prestacao>
                </default>
            </canais-de-prestacao>
        </etapa>
    </etapas>
    <orgao id="http://estruturaorganizacional.dados.gov.br/id/unidade-organizacional/1988" dbId="37525">
        <nomeOrgao>Ministério da Ciência, Tecnologia, Inovações e Comunicações (MCTIC)</nomeOrgao>
    </orgao>
    <segmentos-da-sociedade>
        <item idSegmento="3" idServicoSegmento="3778">Empresas</item>
    </segmentos-da-sociedade>
    <areas-de-interesse>
        <item>Economia e Finanças</item>
        <item>Encargos financeiros</item>
        <item>Empreendedorismo</item>
        <item>Tributação</item>
    </areas-de-interesse>
    <palavras-chave>
        <item id="5796">benefício fiscal</item>
        <item id="5797">inovação</item>
        <item id="5798">desenvolvimento tecnológico</item>
    </palavras-chave>
</servico>
