<?xml version="1.0" encoding="UTF-8" standalone="yes"?>
<servico xsi:schemaLocation="http://servicos.gov.br/v3/schema.../servico.xsd" xmlns="http://servicos.gov.br/v3/schema" xmlns:xsi="http://www.w3.org/2001/XMLSchema-instance">
    <id>registrar-estabelecimento-industrial-e-comercial-de-material-de-multiplicacao-animal</id>
    <dbId>941</dbId>
    <nome>Registrar estabelecimento industrial e comercial de material de multiplicação animal.</nome>
    <sigla></sigla>
    <nomes-populares>
        <item id="730">Não</item>
    </nomes-populares>
    <descricao>Autorização concedida pelo Ministério da Agricultura para realização de coleta, processamento e comercialização de material de multiplicação animal, após verificação do cumprimento dos requisitos dispostos em normativas.  Aplica-se somente a pessoas jurídicas (pessoas físicas não podem realizar a coleta/processamento e comércio de material de multiplicação animal. O resultado é que a empresa está autorizada a realizar a coleta, processamento e/ou comércio de material de multiplicação animal, tornando possível a oferta de sêmen e embrião animal com qualidade, identidade e inócuo.</descricao>
    <contato></contato>
    <gratuito>true</gratuito>
    <porcentagem-manual>false</porcentagem-manual>
    <solicitantes>
        <solicitante id="1072">
            <tipo>Empresas privadas</tipo>
            <requisitos></requisitos>
        </solicitante>
        <solicitante id="1073">
            <tipo>Empresas públicas ou de economia mista</tipo>
            <requisitos></requisitos>
        </solicitante>
    </solicitantes>
    <tempo-total-estimado>
        <atendimento-imediato/>
        <descricao>Não se aplica \ Não é estimado ainda.</descricao>
    </tempo-total-estimado>
    <validade-documento>
        <descricao></descricao>
    </validade-documento>
    <etapas>
        <etapa id="2452">
            <titulo>Requerer registro</titulo>
            <descricao>Apresentação de requerimento de registro na Superintendência Federal do MAPA, acompanhado da devida documentação.</descricao>
            <documentos>
                <default>
                    <item id="2784">Ata de fundação</item>
                    <item id="2785">Carteira de identidade</item>
                    <item id="2786">Certidões de cartório</item>
                    <item id="2787">CNPJ</item>
                    <item id="2788">Contrato Social</item>
                    <item id="2789">Procuração do representante legal</item>
                    <item id="2790">memorial descritivo, planta das edificações, carteria do CRMV, Anotação de Responsabilidade Técnica</item>
                </default>
            </documentos>
            <custos>
                <default/>
            </custos>
            <canais-de-prestacao>
                <default>
                    <canal-de-prestacao id="3142" tipo="presencial">
                        <descricao>Superintendência Federal de Agricultura, pecuária e Abastecimento no estado.</descricao>
                    </canal-de-prestacao>
                </default>
            </canais-de-prestacao>
        </etapa>
        <etapa id="2453">
            <titulo>Receber vistoria pré-registro.</titulo>
            <descricao></descricao>
            <documentos>
                <default>
                    <item id="2791">Nenhum</item>
                </default>
            </documentos>
            <custos>
                <default/>
            </custos>
            <canais-de-prestacao>
                <default>
                    <canal-de-prestacao id="3143" tipo="presencial">
                        <descricao>No próprio estabelecimento solicitante.</descricao>
                    </canal-de-prestacao>
                </default>
            </canais-de-prestacao>
        </etapa>
        <etapa id="2454">
            <titulo>Receber certificado de registro.</titulo>
            <descricao></descricao>
            <documentos>
                <default>
                    <item id="2792">Nenhum</item>
                </default>
            </documentos>
            <custos>
                <default/>
            </custos>
            <canais-de-prestacao>
                <default>
                    <canal-de-prestacao id="3144" tipo="presencial">
                        <descricao>Superintendência Federal de Agricultura no estado.</descricao>
                    </canal-de-prestacao>
                </default>
            </canais-de-prestacao>
        </etapa>
    </etapas>
    <orgao id="http://estruturaorganizacional.dados.gov.br/id/unidade-organizacional/14" dbId="37524">
        <nomeOrgao>Ministério da Agricultura Pecuária e Abastecimento (MAPA)</nomeOrgao>
    </orgao>
    <segmentos-da-sociedade>
        <item idSegmento="3" idServicoSegmento="2731">Empresas</item>
    </segmentos-da-sociedade>
    <areas-de-interesse>
        <item>Agropecuária</item>
    </areas-de-interesse>
    <palavras-chave>
        <item id="2508">multiplicação animal</item>
        <item id="2509">inseminação artificial</item>
        <item id="2510">procriação</item>
        <item id="2511">autorização</item>
    </palavras-chave>
    <legislacoes>
        <item id="802">-</item>
    </legislacoes>
</servico>
