<?xml version="1.0" encoding="UTF-8" standalone="yes"?>
<servico xsi:schemaLocation="http://servicos.gov.br/v3/schema.../servico.xsd" xmlns="http://servicos.gov.br/v3/schema" xmlns:xsi="http://www.w3.org/2001/XMLSchema-instance">
    <id>requerer-habilitacao-disponibilidade-de-area-para-pesquisa-mineral</id>
    <dbId>3107</dbId>
    <nome>Requerer Habilitação - Disponibilidade de área para Pesquisa Mineral</nome>
    <sigla></sigla>
    <nomes-populares>
        <item id="2373">Licitação de áreas</item>
    </nomes-populares>
    <descricao>Requerimento, por meio de formulário padronizado de pré-requerimento eletrônico, a ser preenchido no sítio do DNPM na internet, impresso e protocolizado no DNPM, admitido encaminhamento pelo correio com aviso de recebimento (AR). O pré-requerimento deve ser protocolizado em até 30 dias, contados do seu preenchimento.Requerimento de habilitação aplicado para áreas desoneradas colocadas em disponibilidade pelo DNPM, para fins de pesquisa ou lavra, conforme o caso, nos regimes de autorização de pesquisa, concessão de lavra e permissão de lavra garimpeira. A habilitação serve para a totalidade ou parte da área colocada em disponibilidade para pesquisa ou lavra, e pode objetivar qualquer substância mineral com o ambiente geológico quando se tratar de disponibilidade para pesquisa. A existência de débito com o DNPM inscrito em dívida ativa ou no Cadastro Informativo de Créditos não Quitados do Setor Público Federal - Cadin, que não se encontre com a exigibilidade suspensa impede, até a regularização da situação, da participação em procedimento de disponibilidade de área, quando o devedor for o proponente no procedimento de disponibilidade. Decreto-Lei nº 227/1967 (Código Mineração) Portaria DNPM nº 155/2016</descricao>
    <contato>dgtm.diretoria.gov.br</contato>
    <gratuito>false</gratuito>
    <porcentagem-manual>false</porcentagem-manual>
    <servico-digital>false</servico-digital>
    <link-servico-digital></link-servico-digital>
    <solicitantes>
        <solicitante id="3694">
            <tipo>Mineradores e empresas mineradoras</tipo>
            <requisitos></requisitos>
        </solicitante>
    </solicitantes>
    <tempo-total-estimado>
        <nao-estimado-ainda/>
        <descricao></descricao>
    </tempo-total-estimado>
    <validade-documento>
        <descricao></descricao>
    </validade-documento>
    <etapas>
        <etapa id="7085">
            <titulo>Requerer habilitação</titulo>
            <descricao>cadastramento de dados, protocolização, acompanhamento do processo.</descricao>
            <documentos>
                <default>
                    <item id="9845">Carteira de identidade</item>
                    <item id="9846">Carteira de trabalho</item>
                    <item id="9847">CNPJ</item>
                    <item id="9848">Comprovante de endereço/residência</item>
                    <item id="9849">Comprovante de pagamento</item>
                    <item id="9850">Contrato Social</item>
                    <item id="9851">CPF</item>
                    <item id="9852">Procuração do representante legal</item>
                    <item id="9853">Registro da Junta Comercial</item>
                    <item id="9854">Requerimento eletrônico impresso e assinado</item>
                </default>
            </documentos>
            <custos>
                <default>
                    <custo id="650">
                        <descricao>Taxa de Emolumentos</descricao>
                        <moeda>R$</moeda>
                        <valor>874,62</valor>
                        <valorVariavel></valorVariavel>
                        <statusCustoVariavel>0</statusCustoVariavel>
                    </custo>
                </default>
            </custos>
            <canais-de-prestacao>
                <default>
                    <canal-de-prestacao id="7409" tipo="presencial">
                        <descricao>**DNPM - Departamento Nacional de Produção Mineral (Edifício Sede)** - S.A.N. Quadra 01 Bloco B - CEP: 70041-903 - Brasília/DF</descricao>
                    </canal-de-prestacao>
                    <canal-de-prestacao id="7410" tipo="postal">
                        <descricao>**DNPM - Departamento Nacional de Produção Mineral (Edifício Sede)** - S.A.N. Quadra 01 Bloco B - CEP: 70041-903 - Brasília/DF</descricao>
                    </canal-de-prestacao>
                </default>
                <caso id="817" descricao="Para preenchimento do requerimento eletrônico">
                    <canal-de-prestacao id="7408" tipo="web">
                        <descricao>https://sistemas.dnpm.gov.br/SCM/Extra/site/requerimento/preencherRequerimento.aspx?codigoTipoRequerimento=11</descricao>
                    </canal-de-prestacao>
                </caso>
                <caso id="818" descricao="Para geração do boleto">
                    <canal-de-prestacao id="7411" tipo="web">
                        <descricao>https://sistemas.dnpm.gov.br/dipar_externo/cobranca/emolumentos.asp</descricao>
                    </canal-de-prestacao>
                </caso>
            </canais-de-prestacao>
        </etapa>
    </etapas>
    <orgao id="http://estruturaorganizacional.dados.gov.br/id/unidade-organizacional/1918" dbId="23734">
        <nomeOrgao>Departamento Nacional de Produção Mineral (DNPM)</nomeOrgao>
    </orgao>
    <segmentos-da-sociedade>
        <item idSegmento="3" idServicoSegmento="6979">Empresas</item>
        <item idSegmento="4" idServicoSegmento="6980">Demais segmentos (ONGs, organizações sociais, etc)</item>
        <item idSegmento="1" idServicoSegmento="6981">Cidadãos</item>
    </segmentos-da-sociedade>
    <areas-de-interesse>
        <item>Indústria</item>
        <item>Mineração</item>
    </areas-de-interesse>
    <palavras-chave>
        <item id="13027">pesquisa</item>
        <item id="13028">mineração</item>
        <item id="13029">mudança</item>
    </palavras-chave>
</servico>
